fastapi_users_db_sqlalchemy_pelicanq/__init__.py
fastapi_users_db_sqlalchemy_pelicanq/access_token.py
fastapi_users_db_sqlalchemy_pelicanq/generics.py
fastapi_users_db_sqlalchemy_pelicanq/py.typed
fastapi_users_db_sqlalchemy_pelicanq-6.0.6.dist-info/METADATA
fastapi_users_db_sqlalchemy_pelicanq-6.0.6.dist-info/WHEEL
fastapi_users_db_sqlalchemy_pelicanq-6.0.6.dist-info/licenses/LICENSE
fastapi_users_db_sqlalchemy_pelicanq-6.0.6.dist-info/RECORD
